README.md
setup.cfg
setup.py
eis/__init__.py
eis/publicapi/__init__.py
eis/publicapi/api_client.py
eis/publicapi/configuration.py
eis/publicapi/exceptions.py
eis/publicapi/model_utils.py
eis/publicapi/rest.py
eis/publicapi/api/__init__.py
eis/publicapi/api/address_completions_validations_api.py
eis/publicapi/api/booking_funnels_api.py
eis/publicapi/api/default_api.py
eis/publicapi/api/documents_api.py
eis/publicapi/api/leads_api.py
eis/publicapi/api/named_ranges_api.py
eis/publicapi/api/notifications_api.py
eis/publicapi/api/payments_setup_api.py
eis/publicapi/api/product_versions_api.py
eis/publicapi/api/products_api.py
eis/publicapi/apis/__init__.py
eis/publicapi/model/__init__.py
eis/publicapi/model/address_completion_item_class.py
eis/publicapi/model/address_completion_response_class.py
eis/publicapi/model/address_field_score_class.py
eis/publicapi/model/bank_transfer_dto.py
eis/publicapi/model/bank_transfer_response_class.py
eis/publicapi/model/billing_address_dto.py
eis/publicapi/model/billing_address_response_class.py
eis/publicapi/model/booking_funnel_class.py
eis/publicapi/model/calculate_product_fields_request_dto.py
eis/publicapi/model/calculate_product_fields_response_class.py
eis/publicapi/model/card_details_dto.py
eis/publicapi/model/complete_adyen_payment_setup_request_dto.py
eis/publicapi/model/complete_braintree_payment_setup_request_dto.py
eis/publicapi/model/complete_eis_payment_setup_request_dto.py
eis/publicapi/model/complete_email_verification_dto.py
eis/publicapi/model/complete_email_verification_response_class.py
eis/publicapi/model/complete_payment_setup_request_dto.py
eis/publicapi/model/complete_payment_setup_response_class.py
eis/publicapi/model/complete_stripe_payment_setup_request_dto.py
eis/publicapi/model/create_account_request_dto.py
eis/publicapi/model/create_bank_account_request_dto.py
eis/publicapi/model/create_custom_application_request_dto.py
eis/publicapi/model/create_custom_application_response_class.py
eis_publicapi.egg-info/PKG-INFO
eis_publicapi.egg-info/SOURCES.txt
eis_publicapi.egg-info/dependency_links.txt
eis_publicapi.egg-info/requires.txt
eis_publicapi.egg-info/top_level.txt
