Metadata-Version: 2.1
Name: eis-publicapi
Version: 1.30.0
Summary: Emil PublicAPI
Home-page: UNKNOWN
Author: Contact us
Author-email: kontakt@emil.de
License: UNKNOWN
Keywords: OpenAPI,OpenAPI-Generator,Emil PublicAPI
Platform: UNKNOWN
Requires-Python: >=3.6
